{"version":1,"resource":"file:///home/imad-07/forum/app/api/comments/adder.go","entries":[{"id":"Tpmw.go","timestamp":1736955792800},{"id":"DxZv.go","timestamp":1736955819780},{"id":"oKRj.go","timestamp":1736955926592},{"id":"OEeH.go","source":"Organize Imports","timestamp":1736955926800},{"id":"lEw9.go","timestamp":1736955929476},{"id":"SKXV.go","source":"Organize Imports","timestamp":1736955929816},{"id":"iTMF.go","timestamp":1736955955553},{"id":"IyRP.go","timestamp":1736956028929},{"id":"LOKO.go","timestamp":1736956066893},{"id":"0rto.go","timestamp":1736956078657},{"id":"gbms.go","timestamp":1736956114173},{"id":"baTx.go","source":"undoRedo.source","timestamp":1736956117889},{"id":"Mnvx.go","timestamp":1736956139410},{"id":"G9VL.go","timestamp":1736956890959},{"id":"zE2K.go","timestamp":1736985122234},{"id":"nBY4.go","timestamp":1736985230695},{"id":"pSVV.go","timestamp":1736985246219},{"id":"6c4N.go","timestamp":1736985257703},{"id":"Lkea.go","timestamp":1736985369136},{"id":"hsq2.go","timestamp":1736987750537},{"id":"TIIo.go","timestamp":1737153322756},{"id":"14ps.go","timestamp":1737153334284},{"id":"7jhg.go","timestamp":1737153405476},{"id":"h2f6.go","timestamp":1737153424981},{"id":"SEKq.go","timestamp":1737153467589},{"id":"81pV.go","timestamp":1737153489937},{"id":"gwAN.go","timestamp":1737153519045},{"id":"R0nB.go","timestamp":1737153934332},{"id":"BZ2g.go","source":"Organize Imports","timestamp":1737153939356},{"id":"duqJ.go","timestamp":1737154114570},{"id":"oeTX.go","source":"Organize Imports","timestamp":1737154115398},{"id":"3cQe.go","timestamp":1737203481027},{"id":"DOzo.go","timestamp":1737203545158},{"id":"SdP8.go","timestamp":1737203572929},{"id":"FTkC.go","timestamp":1737203705900},{"id":"hnYZ.go","timestamp":1737203717352},{"id":"YNCD.go","timestamp":1737203766344},{"id":"pYGn.go","timestamp":1737571988755},{"id":"8MYZ.go","timestamp":1737572014368},{"id":"l4dw.go","timestamp":1737572156054},{"id":"ZJ2C.go","timestamp":1737572168473},{"id":"Ujo8.go","timestamp":1737572199854},{"id":"i24z.go","timestamp":1737572240663},{"id":"YWGY.go","timestamp":1737572252809},{"id":"Bv1J.go","timestamp":1737572334044},{"id":"Ei5V.go","timestamp":1737572345333},{"id":"aV7K.go","timestamp":1737572891114},{"id":"Qicc.go","timestamp":1737572923954},{"id":"lIOi.go","source":"Organize Imports","timestamp":1737573017333},{"id":"N2UK.go","source":"undoRedo.source","timestamp":1737574096988}]}